{
  "type": "farmersdelight:cooking",
  "container": {
    "count": 1,
    "id": "albod:empty_jar"
  },
  "experience": 4.0,
  "cookingtime": 250,
  "ingredients": [
    {
      "item": "albod:blueberries"
    },
    {
      "item": "albod:blueberries"
    },
    {
      "item": "albod:blueberries"
    },
    {
      "item": "albod:gelatin_powder"
    },
    {
      "item": "minecraft:sugar"
    }
  ],
  "recipe_book_tab": "misc",
  "result": {
    "count": 1,
    "id": "albod:blueberry_jam"
  }
}